nextstrain/sphinx/theme/VERSION
nextstrain/sphinx/theme/__init__.py
nextstrain/sphinx/theme/breadcrumbs.html
nextstrain/sphinx/theme/footer.html
nextstrain/sphinx/theme/layout.html
nextstrain/sphinx/theme/theme.conf
nextstrain/sphinx/theme/static/favicon.ico
nextstrain/sphinx/theme/static/nextstrain-logo.svg
nextstrain/sphinx/theme/static/css/nextstrain.css
nextstrain/sphinx/theme/static/js/theme.js
nextstrain/sphinx/theme/static/logos/bz_logo.png
nextstrain/sphinx/theme/static/logos/fred-hutch-logo-small.png
nextstrain/sphinx/theme/static/logos/icon.png
nextstrain/sphinx/theme/static/logos/mapbox-logo-black.svg
nextstrain/sphinx/theme/static/logos/nextstrain-logo-small.png
nextstrain/sphinx/theme/static/logos/nextstrain_should_be_svg.png
nextstrain/sphinx/theme/static/logos/nih-logo-small.png
nextstrain/sphinx/theme/static/logos/nih-logo.jpg
nextstrain/sphinx/theme/static/logos/osp-logo-small.png
nextstrain/sphinx/theme/static/logos/sib-logo.png
nextstrain/sphinx/theme/static/logos/unibas-logo.svg
nextstrain_sphinx_theme-2025.1.dist-info/licenses/LICENSE
nextstrain_sphinx_theme-2025.1.dist-info/METADATA
nextstrain_sphinx_theme-2025.1.dist-info/WHEEL
nextstrain_sphinx_theme-2025.1.dist-info/entry_points.txt
nextstrain_sphinx_theme-2025.1.dist-info/top_level.txt
nextstrain_sphinx_theme-2025.1.dist-info/RECORD
