Metadata-Version: 2.4
Name: nextstrain-sphinx-theme
Version: 2025.1
Summary: Nextstrain theme for Sphinx and Read The Docs
Author: Thomas Sibley
Author-email: tsibley@fredhutch.org
License: MIT
Classifier: Framework :: Sphinx
Classifier: Framework :: Sphinx :: Theme
Classifier: Development Status :: 5 - Production/Stable
Classifier: License :: OSI Approved :: MIT License
Classifier: Environment :: Console
Classifier: Environment :: Web Environment
Classifier: Intended Audience :: Developers
Classifier: Operating System :: OS Independent
Classifier: Topic :: Documentation
Classifier: Topic :: Software Development :: Documentation
License-File: LICENSE
Requires-Dist: sphinx_rtd_theme>=1.0.0
Requires-Dist: sphinx-better-subsection
Requires-Dist: sphinx-copybutton
Dynamic: author
Dynamic: author-email
Dynamic: classifier
Dynamic: description
Dynamic: license
Dynamic: license-file
Dynamic: requires-dist
Dynamic: summary
